AdroitFisherman/Base64Utility.cp310-win_amd64.pyd
AdroitFisherman/CircularSingleLinkedList.cp310-win_amd64.pyd
AdroitFisherman/DoubleLinkedList.cp310-win_amd64.pyd
AdroitFisherman/LinkedStack.cp310-win_amd64.pyd
AdroitFisherman/SHAUtility.cp310-win_amd64.pyd
AdroitFisherman/SequentialList.cp310-win_amd64.pyd
AdroitFisherman/SingleLinkedList.cp310-win_amd64.pyd
AdroitFisherman/SingleLinkedListWithoutHeadNode.cp310-win_amd64.pyd
AdroitFisherman/Utilities/Base64Util.py
AdroitFisherman/Utilities/CircularSingleLinkedList.py
AdroitFisherman/Utilities/DoubleLinkedList.py
AdroitFisherman/Utilities/LinkedStack.py
AdroitFisherman/Utilities/SHAUtil.py
AdroitFisherman/Utilities/SequentialList.py
AdroitFisherman/Utilities/SingleLinkedList.py
AdroitFisherman/Utilities/SingleLinkedListWithoutHeadNode.py
AdroitFisherman/Utilities/__init__.py
AdroitFisherman/Utilities/__pycache__/SingleLinkedList.cpython-310.pyc
AdroitFisherman/Utilities/__pycache__/__init__.cpython-310.pyc
AdroitFisherman-0.0.31.dist-info/METADATA
AdroitFisherman-0.0.31.dist-info/WHEEL
AdroitFisherman-0.0.31.dist-info/top_level.txt
AdroitFisherman-0.0.31.dist-info/RECORD
