Metadata-Version: 2.1
Name: AdroitFisherman
Version: 0.0.31
Summary: This is a simple package about Data Structure packed by C/C++ language.
Home-page: UNKNOWN
Author: adroit_fisherman
Author-email: 1295284735@qq.com
License: UNKNOWN
Platform: Windows
Classifier: Development Status :: 2 - Pre-Alpha
Classifier: Natural Language :: Chinese (Simplified)
Classifier: Operating System :: Microsoft :: Windows :: Windows 10
Classifier: Operating System :: Microsoft :: Windows :: Windows 11
Classifier: Programming Language :: C++
Classifier: Programming Language :: Python :: 3.11
Classifier: Programming Language :: Python :: 3.10
Classifier: Programming Language :: Python :: 3.9
Classifier: Topic :: Utilities
